pulumi_venafi/__init__.py
pulumi_venafi/_utilities.py
pulumi_venafi/certificate.py
pulumi_venafi/cloud_keystore_installation.py
pulumi_venafi/get_cloud_keystore.py
pulumi_venafi/get_cloud_provider.py
pulumi_venafi/policy.py
pulumi_venafi/provider.py
pulumi_venafi/pulumi-plugin.json
pulumi_venafi/py.typed
pulumi_venafi/ssh_certificate.py
pulumi_venafi/ssh_config.py
pulumi_venafi/config/__init__.py
pulumi_venafi/config/__init__.pyi
pulumi_venafi/config/vars.py
pulumi_venafi-1.12.2.dist-info/METADATA
pulumi_venafi-1.12.2.dist-info/WHEEL
pulumi_venafi-1.12.2.dist-info/top_level.txt
pulumi_venafi-1.12.2.dist-info/RECORD
